LICENSE
README.md
setup.py
BayesLDM/BayesLDM.py
BayesLDM/__init__.py
BayesLDM/utils.py
BayesLDM.egg-info/PKG-INFO
BayesLDM.egg-info/SOURCES.txt
BayesLDM.egg-info/dependency_links.txt
BayesLDM.egg-info/entry_points.txt
BayesLDM.egg-info/requires.txt
BayesLDM.egg-info/top_level.txt