Metadata-Version: 2.1
Name: BayesLDM
Version: 1.0.9
Summary: BayesLDM
Home-page: https://github.com/reml-lab/BayesLDM/
Author: BayesLDM developer
Author-email: bayesldm@gmail.com
License: MIT
Keywords: mHealth machine-learning data-analysis
Classifier: Development Status :: 5 - Production/Stable
Classifier: Intended Audience :: Healthcare Industry
Classifier: Intended Audience :: Science/Research
Classifier: License :: OSI Approved :: MIT License
Classifier: Natural Language :: English
Classifier: Programming Language :: Python :: 3
Classifier: Topic :: Scientific/Engineering :: Information Analysis
Classifier: Topic :: System :: Distributed Computing
License-File: LICENSE
